{"Adjustments": [{"Products": [{"PartNumber": "24130209", "Quantity": "5", "Date": "2021/12/15"}, {"PartNumber": "22191096", "Quantity": "2", "Date": null}, {"PartNumber": "PD511229", "Quantity": "3", "Date": null}, {"PartNumber": "AB151074", "Quantity": "1", "Date": null}, {"PartNumber": "DJ151071", "Quantity": "-10", "Date": null}, {"PartNumber": "DH101188", "Quantity": "-3", "Date": null}, {"PartNumber": "DU151010", "Quantity": "-1", "Date": null}, {"PartNumber": "DH101154", "Quantity": "-10", "Date": null}, {"PartNumber": "DJ101076", "Quantity": "-10", "Date": null}, {"PartNumber": "DM101140", "Quantity": "-10", "Date": null}, {"PartNumber": "DM101139", "Quantity": "-10", "Date": null}, {"PartNumber": "24201277", "Quantity": "-1", "Date": null}, {"PartNumber": "AM191005", "Quantity": "-10", "Date": null}, {"PartNumber": "AA191071", "Quantity": "-4", "Date": null}, {"PartNumber": "JD511010", "Quantity": "-10", "Date": null}, {"PartNumber": "DD111048", "Quantity": "-10", "Date": null}, {"PartNumber": "DH111015", "Quantity": "-6", "Date": null}, {"PartNumber": "DH111013", "Quantity": "-6", "Date": null}, {"PartNumber": "JB551411", "Quantity": "-2", "Date": null}, {"PartNumber": "JBt51408", "Quantity": "-2", "Date": null}]}]}