{"Adjustments": [{"Products": [{"PartNumber": "DK101570", "Quantity": "-1", "Date": "2022/07/31"}, {"PartNumber": "DK101571", "Quantity": "-1", "Date": null}, {"PartNumber": "DK151094", "Quantity": "-1", "Date": null}, {"PartNumber": "DE151037", "Quantity": "-1", "Date": null}, {"PartNumber": "JD521002", "Quantity": "-1", "Date": null}, {"PartNumber": "JZ511016", "Quantity": "-1", "Date": null}, {"PartNumber": "JE511022", "Quantity": "-1", "Date": null}, {"PartNumber": "DF161425", "Quantity": "-1", "Date": null}, {"PartNumber": "DD101495(YL)", "Quantity": "-1", "Date": null}, {"PartNumber": "AF111010", "Quantity": "-1", "Date": "2022/08/01"}, {"PartNumber": "AA201012", "Quantity": "-1", "Date": null}, {"PartNumber": "AF191007", "Quantity": "1", "Date": "2022/08/02"}, {"PartNumber": "DU201008", "Quantity": "1", "Date": null}, {"PartNumber": "DK101569", "Quantity": "1", "Date": "2022/08/03"}, {"PartNumber": "AP201026", "Quantity": "2", "Date": null}, {"PartNumber": "36DU1503", "Quantity": "-5", "Date": null}, {"PartNumber": "31101041", "Quantity": "-3", "Date": null}, {"PartNumber": "DH101125", "Quantity": "-5", "Date": null}, {"PartNumber": "DP171006", "Quantity": "-4", "Date": null}, {"PartNumber": "36DD4008", "Quantity": "-3", "Date": null}, {"PartNumber": "39201719", "Quantity": "-1", "Date": null}, {"PartNumber": "DH191001", "Quantity": "-1", "Date": null}, {"PartNumber": "DJ191081", "Quantity": "-1", "Date": null}, {"PartNumber": "DU151010", "Quantity": "1", "Date": "2022/08/05"}, {"PartNumber": "DS191013", "Quantity": "1", "Date": null}, {"PartNumber": "36DJ4104", "Quantity": "-1", "Date": "2022/08/09"}, {"PartNumber": "JD521002", "Quantity": "-5", "Date": null}, {"PartNumber": "JZ511016", "Quantity": "-5", "Date": null}, {"PartNumber": "36DJ4104", "Quantity": "-5", "Date": null}, {"PartNumber": "DJ221003", "Quantity": "-1", "Date": null}, {"PartNumber": "DJ221004", "Quantity": "-1", "Date": null}, {"PartNumber": "DF101055", "Quantity": "-10", "Date": null}, {"PartNumber": "39097315", "Quantity": "-10", "Date": null}, {"PartNumber": "DD111018", "Quantity": "-5", "Date": null}, {"PartNumber": "36JL0039", "Quantity": "-1", "Date": null}, {"PartNumber": "AA121187", "Quantity": "-3", "Date": null}, {"PartNumber": "JC201016", "Quantity": "1", "Date": null}, {"PartNumber": "DU191006", "Quantity": "1", "Date": "2022/08/08"}, {"PartNumber": "DZ191013", "Quantity": "1", "Date": null}, {"PartNumber": "AA201012", "Quantity": "-1", "Date": null}, {"PartNumber": "DL181080", "Quantity": "-1", "Date": null}, {"PartNumber": "31151060", "Quantity": "-1", "Date": null}, {"PartNumber": "DH101680", "Quantity": "-1", "Date": null}, {"PartNumber": "PD511229", "Quantity": "-1", "Date": null}, {"PartNumber": "36DS1004", "Quantity": "-1", "Date": null}, {"PartNumber": "DU151018", "Quantity": "-1", "Date": null}, {"PartNumber": "AP111023", "Quantity": "-1", "Date": null}, {"PartNumber": "PA181283", "Quantity": "1", "Date": null}, {"PartNumber": "DX101053", "Quantity": "1", "Date": null}, {"PartNumber": "52JL0339", "Quantity": "1", "Date": null}, {"PartNumber": "JC101038", "Quantity": "-1", "Date": "2022/08/06"}, {"PartNumber": "DH101050", "Quantity": "-1", "Date": null}, {"PartNumber": "DD121013", "Quantity": "-1", "Date": null}, {"PartNumber": "DS141014", "Quantity": "-1", "Date": null}, {"PartNumber": "DU141095", "Quantity": "-1", "Date": null}, {"PartNumber": "36DU1001", "Quantity": "-1", "Date": null}, {"PartNumber": "DL181080", "Quantity": "-1", "Date": null}, {"PartNumber": "JB581005", "Quantity": "-1", "Date": null}, {"PartNumber": "JY551402", "Quantity": "-1", "Date": null}, {"PartNumber": "28101198", "Quantity": "-1", "Date": null}, {"PartNumber": "DJ151033", "Quantity": "-1", "Date": null}, {"PartNumber": "AA101013", "Quantity": "-10", "Date": null}, {"PartNumber": "AA101512", "Quantity": "-5", "Date": null}, {"PartNumber": "PA231600", "Quantity": "-1", "Date": null}, {"PartNumber": "PA231206", "Quantity": "-1", "Date": null}, {"PartNumber": "PA231600", "Quantity": "1", "Date": null}, {"PartNumber": "PA221206", "Quantity": "1", "Date": null}, {"PartNumber": "AA201313", "Quantity": "1", "Date": null}, {"PartNumber": "PA402440", "Quantity": "1", "Date": null}, {"PartNumber": "AA111107", "Quantity": "1", "Date": "2022/08/10"}, {"PartNumber": "39188020", "Quantity": "1", "Date": null}, {"PartNumber": "DK151094", "Quantity": "-1", "Date": null}, {"PartNumber": "AA111153", "Quantity": "-2", "Date": null}, {"PartNumber": "DU201008", "Quantity": "-2", "Date": null}, {"PartNumber": "DU201010", "Quantity": "-2", "Date": null}, {"PartNumber": "DJ201206", "Quantity": "-2", "Date": null}, {"PartNumber": "DJ201207", "Quantity": "-2", "Date": null}, {"PartNumber": "31101033", "Quantity": "-5", "Date": null}, {"PartNumber": "DK101064", "Quantity": "-4", "Date": null}, {"PartNumber": "AA101569", "Quantity": "-4", "Date": null}, {"PartNumber": "24141210", "Quantity": "-10", "Date": null}, {"PartNumber": "DG161121(YL)", "Quantity": "-10", "Date": null}, {"PartNumber": "36DD4008", "Quantity": "-5", "Date": null}, {"PartNumber": "DU121009", "Quantity": "-1", "Date": "2022/08/12"}, {"PartNumber": "AB151063", "Quantity": "-1", "Date": null}, {"PartNumber": "30151105", "Quantity": "-1", "Date": null}, {"PartNumber": "24160924", "Quantity": "-2", "Date": null}]}]}