{
  "Invoice": {
    "Numbers": [
      {
        "ID": "Sales of 2021/07/19,20,21",
        "Type": "Other",
        "Products": [
          {
            "STR_PART_NO": "AL201017",
            "INT_QUATITY": 1
          },
          {
            "STR_PART_NO": "39264715",
            "INT_QUATITY": 10
          },
          {
            "STR_PART_NO": "24131009",
            "INT_QUATITY": 1
          },
          {
            "STR_PART_NO": "AN111015",
            "INT_QUATITY": 2
          },
          {
            "STR_PART_NO": "JD181211",
            "INT_QUATITY": 1
          },
          {
            "STR_PART_NO": "JW232601",
            "INT_QUATITY": 1
          },
          {
            "STR_PART_NO": "36JD4104",
            "INT_QUATITY": -1
          },
          {
            "STR_PART_NO": "36DU1205",
            "INT_QUATITY": -5
          },
          {
            "STR_PART_NO": "DH101154",
            "INT_QUATITY": -20
          },
          {
            "STR_PART_NO": "24130105",
            "INT_QUATITY": 1
          },
          {
            "STR_PART_NO": "39215220",
            "INT_QUATITY": 1
          },
          {
            "STR_PART_NO": "JL561401",
            "INT_QUATITY": 1
          },
          {
            "STR_PART_NO": "DL181080",
            "INT_QUATITY": 2
          },
          {
            "STR_PART_NO": "DF221037",
            "INT_QUATITY": 1
          },
          {
            "STR_PART_NO": "DF221007",
            "INT_QUATITY": 1
          },
          {
            "STR_PART_NO": "24171118",
            "INT_QUATITY": -1
          },
          {
            "STR_PART_NO": "BA137173",
            "INT_QUATITY": -1
          },
          {
            "STR_PART_NO": "30151105",
            "INT_QUATITY": -1
          },
          {
            "STR_PART_NO": "DJ191059",
            "INT_QUATITY": -1
          },
          {
            "STR_PART_NO": "36DU4017",
            "INT_QUATITY": -1
          },
          {
            "STR_PART_NO": "31151060",
            "INT_QUATITY": -1
          },
          {
            "STR_PART_NO": "AA191091",
            "INT_QUATITY": -1
          },
          {
            "STR_PART_NO": "16121138",
            "INT_QUATITY": -1
          },
          {
            "STR_PART_NO": "AY141200",
            "INT_QUATITY": 1
          },
          {
            "STR_PART_NO": "31151024",
            "INT_QUATITY": 1
          },
          {
            "STR_PART_NO": "AA101570",
            "INT_QUATITY": 5
          },
          {
            "STR_PART_NO": "DU181031",
            "INT_QUATITY": 1
          },
          {
            "STR_PART_NO": "LCF00001",
            "INT_QUATITY": 6
          },
          {
            "STR_PART_NO": "DH101016",
            "INT_QUATITY": 1
          },
          {
            "STR_PART_NO": "DH101680",
            "INT_QUATITY": 1
          },
          {
            "STR_PART_NO": "DU181032",
            "INT_QUATITY": 1
          },
          {
            "STR_PART_NO": "DZ191014",
            "INT_QUATITY": 1
          },
          {
            "STR_PART_NO": "52PA0532",
            "INT_QUATITY": 1
          },
          {
            "STR_PART_NO": "AA102094",
            "INT_QUATITY": 1
          },
          {
            "STR_PART_NO": "36BA4002",
            "INT_QUATITY": 1
          },
          {
            "STR_PART_NO": "36BA4002",
            "INT_QUATITY": 2
          },
          {
            "STR_PART_NO": "AA101210",
            "INT_QUATITY": 1
          },
          {
            "STR_PART_NO": "AA111085",
            "INT_QUATITY": 1
          },
          {
            "STR_PART_NO": "31101033",
            "INT_QUATITY": 1
          },
          {
            "STR_PART_NO": "36DJ4104",
            "INT_QUATITY": 1
          },
          {
            "STR_PART_NO": "DJ191023",
            "INT_QUATITY": 1
          },
          {
            "STR_PART_NO": "52DZ0046",
            "INT_QUATITY": 1
          }
        ]
      },
      {
        "ID": "Deepthi Inventory - INV00002279",
        "Type": "Other",
        "Products": [
          {
            "STR_PART_NO": "JZ511016",
            "INT_QUATITY": 10
          }
        ]
      },
      {
        "ID": "Nishan Inventory - CB2001339",
        "Type": "Other",
        "Products": [
          {
            "STR_PART_NO": "24231699(YL)",
            "INT_QUATITY": 3
          },
          {
            "STR_PART_NO": "EI004081(VARROC)",
            "INT_QUATITY": 5
          },
          {
            "STR_PART_NO": "EI0501(POWER)",
            "INT_QUATITY": 4
          },
          {
            "STR_PART_NO": "RJ04041(ENDURANCE)",
            "INT_QUATITY": 10
          }
        ]
      }
    ]
  }
}